django_linter/__init__.py
django_linter/__pkginfo__.py
django_linter/main.py
django_linter/checkers/__init__.py
django_linter/checkers/forms.py
django_linter/checkers/layout.py
django_linter/checkers/misc.py
django_linter/checkers/models.py
django_linter/checkers/settings.py
django_linter/checkers/views.py
django_linter/suppressers/__init__.py
django_linter/suppressers/suppress.py
django_linter/transformers/__init__.py
django_linter/transformers/factories.py
django_linter/transformers/models.py
django_linter/transformers/testing.py
django_linter-0.7.dist-info/DESCRIPTION.rst
django_linter-0.7.dist-info/entry_points.txt
django_linter-0.7.dist-info/METADATA
django_linter-0.7.dist-info/metadata.json
django_linter-0.7.dist-info/RECORD
django_linter-0.7.dist-info/top_level.txt
django_linter-0.7.dist-info/WHEEL
